poetry/__init__.py
poetry/__main__.py
poetry/__version__.py
poetry/_vendor/.gitignore
poetry/config.py
poetry/console/__init__.py
poetry/console/application.py
poetry/console/commands/__init__.py
poetry/console/commands/about.py
poetry/console/commands/add.py
poetry/console/commands/build.py
poetry/console/commands/cache/__init__.py
poetry/console/commands/cache/clear.py
poetry/console/commands/check.py
poetry/console/commands/command.py
poetry/console/commands/config.py
poetry/console/commands/debug/__init__.py
poetry/console/commands/debug/info.py
poetry/console/commands/debug/resolve.py
poetry/console/commands/develop.py
poetry/console/commands/init.py
poetry/console/commands/install.py
poetry/console/commands/lock.py
poetry/console/commands/new.py
poetry/console/commands/publish.py
poetry/console/commands/remove.py
poetry/console/commands/run.py
poetry/console/commands/script.py
poetry/console/commands/search.py
poetry/console/commands/self/__init__.py
poetry/console/commands/self/update.py
poetry/console/commands/shell.py
poetry/console/commands/show.py
poetry/console/commands/update.py
poetry/console/commands/venv_command.py
poetry/console/commands/version.py
poetry/console/styles/__init__.py
poetry/console/styles/poetry.py
poetry/exceptions.py
poetry/installation/__init__.py
poetry/installation/base_installer.py
poetry/installation/installer.py
poetry/installation/noop_installer.py
poetry/installation/pip_installer.py
poetry/io/__init__.py
poetry/io/null_io.py
poetry/io/raw_argv_input.py
poetry/json/__init__.py
poetry/json/schemas/poetry-schema.json
poetry/layouts/__init__.py
poetry/layouts/layout.py
poetry/layouts/src.py
poetry/layouts/standard.py
poetry/locations.py
poetry/masonry/__init__.py
poetry/masonry/api.py
poetry/masonry/builder.py
poetry/masonry/builders/__init__.py
poetry/masonry/builders/builder.py
poetry/masonry/builders/complete.py
poetry/masonry/builders/sdist.py
poetry/masonry/builders/wheel.py
poetry/masonry/metadata.py
poetry_plus-0.11.4.dist-info/entry_points.txt
poetry_plus-0.11.4.dist-info/LICENSE
poetry_plus-0.11.4.dist-info/WHEEL
poetry_plus-0.11.4.dist-info/METADATA
poetry_plus-0.11.4.dist-info/RECORD
